acronym/__init__.py
acronym/acronym.py
acronym/scoring.py
acronym-2.0.0.dist-info/METADATA
acronym-2.0.0.dist-info/WHEEL
acronym-2.0.0.dist-info/entry_points.txt
acronym-2.0.0.dist-info/top_level.txt
acronym-2.0.0.dist-info/RECORD
