Metadata-Version: 2.1
Name: acronym
Version: 2.0.0
Summary: ACRONYM (Acronym CReatiON for You and Me)
Home-page: https://github.com/bacook17/acronym
Author: Ben Cook
Author-email: bacook17@gmail.com
License: LICENSE
Platform: UNKNOWN
Classifier: Topic :: Scientific/Engineering :: Astronomy
Requires-Dist: numpy
Requires-Dist: tqdm
Requires-Dist: nltk
Requires-Dist: pandas
